hpackage.py
hpackage-0.2.10.dist-info/licenses/LICENSE
hpackage-0.2.10.dist-info/METADATA
hpackage-0.2.10.dist-info/WHEEL
hpackage-0.2.10.dist-info/entry_points.txt
hpackage-0.2.10.dist-info/top_level.txt
hpackage-0.2.10.dist-info/RECORD
