Metadata-Version: 2.4
Name: hpackage
Version: 0.2.10
Summary: Houdini package manager command-line tool
Author-email: SideFX <support@sidefx.com>
License-Expression: LicenseRef-SideFX-EULA
Project-URL: Homepage, https://www.sidefx.com
Project-URL: Issues, https://www.sidefx.com/support-programs/
Classifier: Programming Language :: Python :: 3
Classifier: Operating System :: OS Independent
Requires-Python: >=3.8
License-File: LICENSE
Requires-Dist: requests>=2.31
Dynamic: license-file
